zk_lib/__init__.py
zk_lib/py_lib.py
zk_lib/setup.py
ycezlib-0.0.4.dist-info/LICENSE
ycezlib-0.0.4.dist-info/METADATA
ycezlib-0.0.4.dist-info/WHEEL
ycezlib-0.0.4.dist-info/top_level.txt
ycezlib-0.0.4.dist-info/RECORD
