Metadata-Version: 2.1
Name: ycezlib
Version: 0.0.4
Summary: Hello,this is zk's lib for python
Home-page: https://gitee.com/xcntime
Author: xcntime
Author-email: xcntime@qq.com
License: GPLv3
Platform: UNKNOWN
Classifier: Programming Language :: Python :: 3
Classifier: License :: OSI Approved :: GNU General Public License v3 (GPLv3)
Classifier: Operating System :: OS Independent
Requires-Python: >=3.0
Requires-Dist: pandas
Requires-Dist: numpy
